{
    "timestamp": 1660390490811,
    "lastTx": "5xcRghTL13nAd86hsgQw57Qgim8Poi7fnJqszg1Wukiy1c4jfYt6QbnDGHeFfTYWY3msHni5EXqSKZzstA8h5bqb",
    "startTx": {
        "blockTime": 1645134616,
        "confirmationStatus": "finalized",
        "err": {
            "InstructionError": [
                1,
                {
                    "Custom": 1
                }
            ]
        },
        "memo": null,
        "signature": "oP4aZ9tCAKaPvSwQZ9Zedy3vc7PkX4zdxrWd6LgmSQBZTzhq8ek2yCy9F91J3dEcpexVyGw9tyx3xBWFZJB6ErL",
        "slot": 121300982
    },
    "volume": 4435908518992,
    "earnings_lamports": 4032351072264,
    "earnings_usdc": 0,
    "startdate": 1645488000,
    "pubkey": "7NsngNMtXJNdHgeK4znQDZ5xVzT2nkGoGRGhMWApejCV"
}